g2pk/__init__.py
g2pk/english.py
g2pk/g2pk.py
g2pk/idioms.txt
g2pk/numerals.py
g2pk/regular.py
g2pk/rules.txt
g2pk/special.py
g2pk/table.csv
g2pk/utils.py
g2pK-0.9.4.dist-info/LICENSE
g2pK-0.9.4.dist-info/METADATA
g2pK-0.9.4.dist-info/WHEEL
g2pK-0.9.4.dist-info/top_level.txt
g2pK-0.9.4.dist-info/RECORD
