Metadata-Version: 2.1
Name: g2pK
Version: 0.9.4
Summary: g2pK: g2p module for Korean
Home-page: https://github.com/Kyubyong/g2pK
Author: Kyubyong Park
Author-email: kbpark.linguist@gmail.com
License: Apache License 2.0
Platform: UNKNOWN
Classifier: Development Status :: 5 - Production/Stable
Classifier: Intended Audience :: Developers
Classifier: Intended Audience :: Science/Research
Classifier: License :: OSI Approved :: Apache Software License
Classifier: Operating System :: OS Independent
Classifier: Programming Language :: Python :: 3
Classifier: Programming Language :: Python :: 3.6
Classifier: Programming Language :: Python :: 3.7
Requires-Python: >=3.6
Requires-Dist: jamo
Requires-Dist: nltk
Requires-Dist: konlpy
Requires-Dist: python-mecab-ko
